s3/__init__.py
s3/_types.py
s3/_utils.py
s3/core.py
s3/s3.py
tests/__init__.py
tests/conftest.py
tests/test_s3.py
yandex_s3-0.1.1.dist-info/LICENSE
yandex_s3-0.1.1.dist-info/METADATA
yandex_s3-0.1.1.dist-info/WHEEL
yandex_s3-0.1.1.dist-info/top_level.txt
yandex_s3-0.1.1.dist-info/RECORD
