Metadata-Version: 2.1
Name: yandex-s3
Version: 0.1.1
Summary: Asyncio compatible SDK for Yandex Object Storage
Home-page: https://github.com/mrslow/yandex-s3
Author: Anton Shchetikhin
Author-email: animal2k@gmail.com
License: MIT
Platform: UNKNOWN
Classifier: Development Status :: 5 - Production/Stable
Classifier: Programming Language :: Python
Classifier: Programming Language :: Python :: 3
Classifier: Programming Language :: Python :: 3 :: Only
Classifier: Programming Language :: Python :: 3.8
Classifier: Programming Language :: Python :: 3.9
Requires-Python: >=3.8
Requires-Dist: aiofiles (>=0.5.0)
Requires-Dist: cryptography (>=3.1.1)
Requires-Dist: httpx (>=0.15.5)
Requires-Dist: pydantic (>=1.6.1)
